fastphase-2.0.3.dist-info/METADATA
fastphase-2.0.3.dist-info/RECORD
fastphase-2.0.3.dist-info/WHEEL
fastphase-2.0.3.dist-info/LICENSE
fastphase-2.0.3.dist-info/top_level.txt
fastphase/fastphase.cpython-311-x86_64-linux-gnu.so
fastphase/fastphase.c
fastphase/params.py
fastphase/__init__.py
fastphase/calc_func.c
fastphase/fastphase.pyx
fastphase/calc_func.cpython-311-x86_64-linux-gnu.so
fastphase/calc_func.pyx
fastphase/fastphase_ray.py
