Metadata-Version: 2.1
Name: fastphase
Version: 2.0.3
Summary: Python implementation of the fastPHASE model
Author-email: Bertrand Servin <bertrand.servin@inrae.fr>
License: LGPL v3
Project-URL: Homepage, https://forgemia.inra.fr/bertrand.servin/fastphase
Classifier: Development Status :: 5 - Production/Stable
Classifier: Intended Audience :: Science/Research
Classifier: License :: OSI Approved :: GNU Lesser General Public License v3 (LGPLv3)
Classifier: Operating System :: OS Independent
Classifier: Programming Language :: Cython
Classifier: Topic :: Scientific/Engineering
Requires-Python: >=3.8
License-File: LICENSE
Requires-Dist: numpy
Requires-Dist: scipy
Requires-Dist: psutil
Requires-Dist: ray
